glyph_sdk/__init__.py
glyph_sdk-0.1.0.dist-info/METADATA
glyph_sdk-0.1.0.dist-info/WHEEL
glyph_sdk-0.1.0.dist-info/top_level.txt
glyph_sdk-0.1.0.dist-info/RECORD
